system_cmd.pyi
system_cmd.cpython-310-aarch64-linux-gnu.so
SystemCmd_z7-7.3.2201261049.dist-info/METADATA
SystemCmd_z7-7.3.2201261049.dist-info/WHEEL
SystemCmd_z7-7.3.2201261049.dist-info/top_level.txt
SystemCmd_z7-7.3.2201261049.dist-info/zip-safe
SystemCmd_z7-7.3.2201261049.dist-info/RECORD
