Metadata-Version: 2.1
Name: SystemCmd-z7
Version: 7.3.2201261049
Summary: UNKNOWN
Home-page: https://github.com/zupermind/PACKAGENAME
Author: Andrea Censi
Author-email: info@zupermind.com
License: UNKNOWN
Platform: UNKNOWN
Requires-Dist: PyContracts3
Requires-Dist: six
Requires-Dist: zuper-commons-z7
Provides-Extra: test
